textalytics_spacy/spacy_entity_recognition.py
textalytics_stanza/stanza_entity_recognition.py
textalytics_oss_adapters-0.1.1.dist-info/entry_points.txt
textalytics_oss_adapters-0.1.1.dist-info/WHEEL
textalytics_oss_adapters-0.1.1.dist-info/METADATA
textalytics_oss_adapters-0.1.1.dist-info/RECORD
